pymediainfo/__init__.py
pymediainfo_pyrofork-6.0.1.dist-info/AUTHORS
pymediainfo_pyrofork-6.0.1.dist-info/LICENSE
pymediainfo_pyrofork-6.0.1.dist-info/METADATA
pymediainfo_pyrofork-6.0.1.dist-info/WHEEL
pymediainfo_pyrofork-6.0.1.dist-info/namespace_packages.txt
pymediainfo_pyrofork-6.0.1.dist-info/top_level.txt
pymediainfo_pyrofork-6.0.1.dist-info/RECORD
