Metadata-Version: 2.1
Name: pymediainfo-pyrofork
Version: 6.0.1
Summary: A Python wrapper for the mediainfo library.
Home-page: https://github.com/Mayuri-Chan/pymediainfo-pyrofork
Author: wulan17
Author-email: mayuri@mayuri.my.id
License: MIT
Project-URL: Documentation, https://pymediainfo.readthedocs.io/
Project-URL: Bugs, https://github.com/Mayuri-Chan/pymediainfo-pyrofork/issues
Classifier: Development Status :: 5 - Production/Stable
Classifier: Programming Language :: Python :: 3.7
Classifier: Programming Language :: Python :: 3.8
Classifier: Programming Language :: Python :: 3.9
Classifier: Programming Language :: Python :: 3.10
Classifier: Programming Language :: Python :: 3.11
Classifier: Programming Language :: Python :: 3 :: Only
Classifier: Programming Language :: Python :: Implementation :: CPython
Classifier: Programming Language :: Python :: Implementation :: PyPy
Classifier: Operating System :: POSIX :: Linux
Classifier: Operating System :: MacOS :: MacOS X
Classifier: Operating System :: Microsoft :: Windows
Classifier: License :: OSI Approved :: MIT License
Requires-Python: >=3.7
License-File: LICENSE
License-File: AUTHORS
Requires-Dist: importlib-metadata ; python_version < "3.8"
